{
  "name": "root",
  "path": "root/",
  "filetype": "folder",
  "filedata": [
    {
      "name": "Users",
      "path": "root/Users/",
      "filetype": "folder",
      "filedata": [
        {
          "name": "Default",
          "path": "root/Users/Default/",
          "filetype": "folder",
          "filedata": [
            {
              "name": "testi.txt",
              "path": "root/Users/Default/testi.txt",
              "filetype": "txt",
              "text": "aa"
            }
          ]
        }
      ]
    },
    {
      "name": "Documents",
      "path": "root/Documents/",
      "filetype": "folder",
      "filedata": [
        {
          "name": "Notes.cr",
          "path": "root/Documents/Notes.cr",
          "filetype": "txt",
          "text": ")\"!JFAPvam*)2#dfbo%0AbfgSAm,0oad+STR_O%0AbfgSAm,0^sdaG=A!kd)4mcakI1"
        }
      ]
    }
  ]
}